README.md
setup.cfg
setup.py
acnawebcli.egg-info/PKG-INFO
acnawebcli.egg-info/SOURCES.txt
acnawebcli.egg-info/dependency_links.txt
acnawebcli.egg-info/entry_points.txt
acnawebcli.egg-info/requires.txt
acnawebcli.egg-info/top_level.txt
cli/__init__.py
cli/authenticate.py
cli/calculator.py
cli/greeter.py
cli/main.py