Metadata-Version: 2.1
Name: acnawebcli
Version: 0.1.0
Summary: CLI for study
Home-page: https://github.com/acnaweb/cli-tools
Author: Antonio Carlos de Lima Junior
Author-email: antonioclj.ac@gmail.com
License: MIT
Keywords: library test
Platform: UNKNOWN
Classifier: Development Status :: 5 - Production/Stable
Classifier: Programming Language :: Python :: 3
Classifier: Operating System :: OS Independent
Classifier: Natural Language :: Portuguese (Brazilian)
Classifier: Natural Language :: English
